{
    "configurations": [
        {
            "name": "Linux",
            "includePath": [
                "${workspaceFolder}/**",
                "/home/kuromoko1212/mujoco-3.1.6/include",
                "/home/kuromoko1212/anaconda3/envs/croco-cpp-3/include",
                "/usr/include/",
                "${workspaceFolder}/LegTrajectory",
                "/usr/include/eigen3"
            ],
            "defines": [],
            "compilerPath": "/usr/bin/gcc",
            "cStandard": "c17",
            "cppStandard": "gnu++14",
            "intelliSenseMode": "linux-gcc-x64"
        }
    ],
    "version": 4
}